git_scribe/__init__.py
git_scribe/main.py
git_scribe/commands/__init__.py
git_scribe/commands/commit.py
git_scribe/commands/init.py
git_scribe/commands/pr.py
git_scribe/core/__init__.py
git_scribe/core/config.py
git_scribe/core/editor.py
git_scribe/core/git_utils.py
git_scribe/core/github.py
git_scribe/core/llm.py
popyson_git_scribe-0.2.6.dist-info/licenses/LICENSE
popyson_git_scribe-0.2.6.dist-info/METADATA
popyson_git_scribe-0.2.6.dist-info/WHEEL
popyson_git_scribe-0.2.6.dist-info/entry_points.txt
popyson_git_scribe-0.2.6.dist-info/top_level.txt
popyson_git_scribe-0.2.6.dist-info/RECORD
