Metadata-Version: 2.4
Name: popyson-git-scribe
Version: 0.2.6
Summary: A CLI tool to generate commit messages and pull requests using LLM.
Author-email: popyson <popyson@example.com>
License: MIT
Project-URL: Homepage, https://github.com/popyson1648/git-scribe
Project-URL: Bug Tracker, https://github.com/popyson1648/git-scribe/issues
Keywords: git,ai,llm,commit,developer-tools,cli
Classifier: Development Status :: 4 - Beta
Classifier: Intended Audience :: Developers
Classifier: License :: OSI Approved :: MIT License
Classifier: Programming Language :: Python :: 3
Classifier: Programming Language :: Python :: 3.8
Classifier: Programming Language :: Python :: 3.9
Classifier: Programming Language :: Python :: 3.10
Classifier: Programming Language :: Python :: 3.11
Classifier: Topic :: Software Development :: Version Control :: Git
Classifier: Topic :: Utilities
Requires-Python: >=3.8
License-File: LICENSE
Requires-Dist: requests
Requires-Dist: gitpython
Requires-Dist: rich
Requires-Dist: typer
Requires-Dist: toml
Provides-Extra: dev
Requires-Dist: pytest; extra == "dev"
Requires-Dist: pytest-mock; extra == "dev"
Requires-Dist: pytest-cov; extra == "dev"
Requires-Dist: pre-commit; extra == "dev"
Requires-Dist: ruff; extra == "dev"
Dynamic: license-file
